rexec/__init__.py
rexec/client_api.py
rexec/remote_obj.py
scidx_rexec-0.0.6.dist-info/licenses/LICENSE
scidx_rexec-0.0.6.dist-info/METADATA
scidx_rexec-0.0.6.dist-info/WHEEL
scidx_rexec-0.0.6.dist-info/top_level.txt
scidx_rexec-0.0.6.dist-info/RECORD
