Metadata-Version: 2.4
Name: scidx-rexec
Version: 0.0.6
Summary: Client library for SciDX Remote Execution
Home-page: https://github.com/sci-ndp/SciDx-rexec
Author: Yutian Qin
Author-email: yutian.qin@utah.edu
License-File: LICENSE
Requires-Dist: packaging==25.0
Requires-Dist: dill==0.4.0
Requires-Dist: pyzmq==26.4.0
Requires-Dist: dxspaces==0.0.8
Requires-Dist: cryptography==45.0.4
Requires-Dist: PyJWT==2.10.1
Dynamic: author
Dynamic: author-email
Dynamic: description
Dynamic: description-content-type
Dynamic: home-page
Dynamic: license-file
Dynamic: requires-dist
Dynamic: summary
